synthcity/__init__.py
synthcity/logger.py
synthcity/version.py
synthcity/benchmark/__init__.py
synthcity/benchmark/utils.py
synthcity/metrics/__init__.py
synthcity/metrics/_utils.py
synthcity/metrics/eval.py
synthcity/metrics/eval_attacks.py
synthcity/metrics/eval_detection.py
synthcity/metrics/eval_performance.py
synthcity/metrics/eval_privacy.py
synthcity/metrics/eval_sanity.py
synthcity/metrics/eval_statistical.py
synthcity/metrics/plots.py
synthcity/metrics/scores.py
synthcity/metrics/weighted_metrics.py
synthcity/metrics/core/__init__.py
synthcity/metrics/core/metric.py
synthcity/metrics/representations/OneClass.py
synthcity/metrics/representations/__init__.py
synthcity/metrics/representations/networks.py
synthcity/plugins/__init__.py
synthcity/plugins/core/__init__.py
synthcity/plugins/core/constraints.py
synthcity/plugins/core/dataloader.py
synthcity/plugins/core/dataset.py
synthcity/plugins/core/distribution.py
synthcity/plugins/core/plugin.py
synthcity/plugins/core/schema.py
synthcity/plugins/core/serializable.py
synthcity/plugins/core/models/RGCNConv.py
synthcity/plugins/core/models/__init__.py
synthcity/plugins/core/models/aim.py
synthcity/plugins/core/models/bnaf.py
synthcity/plugins/core/models/convnet.py
synthcity/plugins/core/models/factory.py
synthcity/plugins/core/models/feature_encoder.py
synthcity/plugins/core/models/flows.py
synthcity/plugins/core/models/functions.py
synthcity/plugins/core/models/gan.py
synthcity/plugins/core/models/goggle.py
synthcity/plugins/core/models/image_gan.py
synthcity/plugins/core/models/layers.py
synthcity/plugins/core/models/mlp.py
synthcity/plugins/core/models/tabnet.py
synthcity/plugins/core/models/tabular_aim.py
synthcity/plugins/core/models/tabular_arf.py
synthcity/plugins/core/models/tabular_encoder.py
synthcity/plugins/core/models/tabular_flows.py
synthcity/plugins/core/models/tabular_gan.py
synthcity/plugins/core/models/tabular_goggle.py
synthcity/plugins/core/models/tabular_great.py
synthcity-0.2.12.dist-info/licenses/LICENSE
synthcity-0.2.12.dist-info/METADATA
synthcity-0.2.12.dist-info/WHEEL
synthcity-0.2.12.dist-info/top_level.txt
synthcity-0.2.12.dist-info/RECORD
