Metadata-Version: 2.4
Name: synthcity
Version: 0.2.12
Summary: Synthetic data generator and evaluator!
License: Apache-2.0 license
Platform: any
Classifier: Programming Language :: Python :: 3
Classifier: Topic :: Scientific/Engineering :: Artificial Intelligence
Classifier: Intended Audience :: Science/Research
Classifier: Operating System :: OS Independent
Requires-Python: >=3.9
License-File: LICENSE
Requires-Dist: importlib-metadata
Requires-Dist: pandas>=2.1
Requires-Dist: torch<2.3,>=2.1
Requires-Dist: scikit-learn>=1.2
Requires-Dist: nflows>=0.14
Requires-Dist: numpy<2.0,>=1.20
Requires-Dist: lifelines<0.30.0,>=0.29.0
Requires-Dist: opacus>=1.3
Requires-Dist: networkx<3.0,>2.0
Requires-Dist: decaf-synthetic-data>=0.1.6
Requires-Dist: optuna>=3.1
Requires-Dist: shap
Requires-Dist: tenacity
Requires-Dist: tqdm
Requires-Dist: loguru
Requires-Dist: pydantic>=2.0
Requires-Dist: cloudpickle
Requires-Dist: scipy
Requires-Dist: xgboost<3.0.0
Requires-Dist: geomloss
Requires-Dist: pgmpy<1.0
Requires-Dist: redis
Requires-Dist: pycox
Requires-Dist: xgbse>=0.3.1
Requires-Dist: pykeops
Requires-Dist: fflows
Requires-Dist: monai
Requires-Dist: tsai; python_version > "3.7"
Requires-Dist: be-great>=0.0.5; python_version >= "3.9"
Requires-Dist: arfpy
Requires-Dist: fastcore<1.8
Requires-Dist: fastai<2.8
Provides-Extra: testing
Requires-Dist: setuptools; extra == "testing"
Requires-Dist: pytest; extra == "testing"
Requires-Dist: pytest-cov; extra == "testing"
Requires-Dist: jupyter; extra == "testing"
Requires-Dist: notebook; extra == "testing"
Requires-Dist: bandit; extra == "testing"
Requires-Dist: black; extra == "testing"
Requires-Dist: black-nb; extra == "testing"
Requires-Dist: darglint; extra == "testing"
Requires-Dist: docutils<0.18; extra == "testing"
Requires-Dist: doc8; extra == "testing"
Requires-Dist: flake8; extra == "testing"
Requires-Dist: isort; extra == "testing"
Requires-Dist: nbconvert; extra == "testing"
Requires-Dist: nbformat; extra == "testing"
Requires-Dist: pytest-benchmark; extra == "testing"
Requires-Dist: pytest-xdist[psutil]; extra == "testing"
Requires-Dist: pytest-xprocess; extra == "testing"
Requires-Dist: igraph; extra == "testing"
Requires-Dist: py; extra == "testing"
Requires-Dist: pre-commit; extra == "testing"
Requires-Dist: tabulate; extra == "testing"
Requires-Dist: click; extra == "testing"
Provides-Extra: goggle
Requires-Dist: dgl; extra == "goggle"
Requires-Dist: torch_geometric; extra == "goggle"
Requires-Dist: torch_sparse; extra == "goggle"
Requires-Dist: torch_scatter; extra == "goggle"
Provides-Extra: all
Requires-Dist: setuptools; extra == "all"
Requires-Dist: pytest; extra == "all"
Requires-Dist: pytest-cov; extra == "all"
Requires-Dist: jupyter; extra == "all"
Requires-Dist: notebook; extra == "all"
Requires-Dist: bandit; extra == "all"
Requires-Dist: black; extra == "all"
Requires-Dist: black-nb; extra == "all"
Requires-Dist: darglint; extra == "all"
Requires-Dist: docutils<0.18; extra == "all"
Requires-Dist: doc8; extra == "all"
Requires-Dist: flake8; extra == "all"
Requires-Dist: isort; extra == "all"
Requires-Dist: nbconvert; extra == "all"
Requires-Dist: nbformat; extra == "all"
Requires-Dist: pytest-benchmark; extra == "all"
Requires-Dist: pytest-xdist[psutil]; extra == "all"
Requires-Dist: pytest-xprocess; extra == "all"
Requires-Dist: igraph; extra == "all"
Requires-Dist: py; extra == "all"
Requires-Dist: pre-commit; extra == "all"
Requires-Dist: tabulate; extra == "all"
Requires-Dist: click; extra == "all"
Requires-Dist: dgl; extra == "all"
Requires-Dist: torch_geometric; extra == "all"
Requires-Dist: torch_sparse; extra == "all"
Requires-Dist: torch_scatter; extra == "all"
Dynamic: license-file
